walutomat_py/__init__.py
walutomat_py/client.py
walutomat_py-0.0.20251110.201342.dist-info/METADATA
walutomat_py-0.0.20251110.201342.dist-info/WHEEL
walutomat_py-0.0.20251110.201342.dist-info/RECORD
